uagents_core/__init__.py
uagents_core/config.py
uagents_core/contrib/__init__.py
uagents_core/contrib/protocols/__init__.py
uagents_core/contrib/protocols/chat/__init__.py
uagents_core/contrib/protocols/subscriptions/__init__.py
uagents_core/envelope.py
uagents_core/helpers.py
uagents_core/identity.py
uagents_core/logger.py
uagents_core/models.py
uagents_core/protocol.py
uagents_core/registration.py
uagents_core/storage.py
uagents_core/types.py
uagents_core/utils/__init__.py
uagents_core/utils/messages.py
uagents_core/utils/registration.py
uagents_core/utils/resolver.py
uagents_core-0.3.1.dist-info/METADATA
uagents_core-0.3.1.dist-info/WHEEL
uagents_core-0.3.1.dist-info/RECORD
